{"lastDay":{"type":"BigNumber","hex":"0x071d93"},"rewards":[{"type":"interest","period":"long","time":{"type":"BigNumber","hex":"0x81"},"amount":{"type":"BigNumber","hex":"0x07c2daf835"}},{"type":"interest","period":"long","time":{"type":"BigNumber","hex":"0x81"},"amount":{"type":"BigNumber","hex":"0x07c2daf835"}},{"type":"interest","period":"long","time":{"type":"BigNumber","hex":"0x81"},"amount":{"type":"BigNumber","hex":"0x07c2daf835"}},{"type":"interest","period":"long","time":{"type":"BigNumber","hex":"0x81"},"amount":{"type":"BigNumber","hex":"0x07c2daf835"}},{"type":"interest","period":"long","time":{"type":"BigNumber","hex":"0x81"},"amount":{"type":"BigNumber","hex":"0x07c2daf835"}},{"type":"interest","period":"long","time":{"type":"BigNumber","hex":"0x81"},"amount":{"type":"BigNumber","hex":"0x07c2daf835"}},{"type":"interest","period":"long","time":{"type":"BigNumber","hex":"0x81"},"amount":{"type":"BigNumber","hex":"0x07c2daf835"}},{"type":"interest","period":"long","time":{"type":"BigNumber","hex":"0x81"},"amount":{"type":"BigNumber","hex":"0x07c2daf835"}},{"type":"interest","period":"long","time":{"type":"BigNumber","hex":"0x81"},"amount":{"type":"BigNumber","hex":"0x07c2daf835"}},{"type":"interest","period":"long","time":{"type":"BigNumber","hex":"0x81"},"amount":{"type":"BigNumber","hex":"0x07c2daf835"}},{"type":"interest","period":"long","time":{"type":"BigNumber","hex":"0x81"},"amount":{"type":"BigNumber","hex":"0x00"}},{"type":"interest","period":"long","time":{"type":"BigNumber","hex":"0x81"},"amount":{"type":"BigNumber","hex":"0x00"}},{"type":"interest","period":"long","time":{"type":"BigNumber","hex":"0x81"},"amount":{"type":"BigNumber","hex":"0x00"}},{"type":"interest","period":"long","time":{"type":"BigNumber","hex":"0x81"},"amount":{"type":"BigNumber","hex":"0x00"}},{"type":"interest","period":"long","time":{"type":"BigNumber","hex":"0x81"},"amount":{"type":"BigNumber","hex":"0x00"}},{"type":"interest","period":"long","time":{"type":"BigNumber","hex":"0x81"},"amount":{"type":"BigNumber","hex":"0x00"}},{"type":"interest","period":"long","time":{"type":"BigNumber","hex":"0x81"},"amount":{"type":"BigNumber","hex":"0x00"}},{"type":"interest","period":"long","time":{"type":"BigNumber","hex":"0x81"},"amount":{"type":"BigNumber","hex":"0x00"}},{"type":"interest","period":"long","time":{"type":"BigNumber","hex":"0x81"},"amount":{"type":"BigNumber","hex":"0x00"}},{"type":"interest","period":"long","time":{"type":"BigNumber","hex":"0x81"},"amount":{"type":"BigNumber","hex":"0x00"}},{"type":"interest","period":"long","time":{"type":"BigNumber","hex":"0x81"},"amount":{"type":"BigNumber","hex":"0x00"}},{"type":"interest","period":"long","time":{"type":"BigNumber","hex":"0x81"},"amount":{"type":"BigNumber","hex":"0x00"}},{"type":"interest","period":"long","time":{"type":"BigNumber","hex":"0x81"},"amount":{"type":"BigNumber","hex":"0x00"}},{"type":"interest","period":"long","time":{"type":"BigNumber","hex":"0x81"},"amount":{"type":"BigNumber","hex":"0x00"}},{"type":"interest","period":"long","time":{"type":"BigNumber","hex":"0x81"},"amount":{"type":"BigNumber","hex":"0x00"}},{"type":"interest","period":"long","time":{"type":"BigNumber","hex":"0x81"},"amount":{"type":"BigNumber","hex":"0x00"}},{"type":"interest","period":"long","time":{"type":"BigNumber","hex":"0x81"},"amount":{"type":"BigNumber","hex":"0x00"}},{"type":"interest","period":"long","time":{"type":"BigNumber","hex":"0x81"},"amount":{"type":"BigNumber","hex":"0x00"}},{"type":"interest","period":"long","time":{"type":"BigNumber","hex":"0x81"},"amount":{"type":"BigNumber","hex":"0x00"}},{"type":"interest","period":"long","time":{"type":"BigNumber","hex":"0x81"},"amount":{"type":"BigNumber","hex":"0x00"}},{"type":"interest","period":"long","time":{"type":"BigNumber","hex":"0x81"},"amount":{"type":"BigNumber","hex":"0x00"}},{"type":"interest","period":"long","time":{"type":"BigNumber","hex":"0x81"},"amount":{"type":"BigNumber","hex":"0x00"}},{"type":"interest","period":"long","time":{"type":"BigNumber","hex":"0x81"},"amount":{"type":"BigNumber","hex":"0x00"}},{"type":"interest","period":"long","time":{"type":"BigNumber","hex":"0x81"},"amount":{"type":"BigNumber","hex":"0x00"}},{"type":"interest","period":"long","time":{"type":"BigNumber","hex":"0x81"},"amount":{"type":"BigNumber","hex":"0x00"}},{"type":"interest","period":"long","time":{"type":"BigNumber","hex":"0x81"},"amount":{"type":"BigNumber","hex":"0x00"}},{"type":"interest","period":"long","time":{"type":"BigNumber","hex":"0x81"},"amount":{"type":"BigNumber","hex":"0x00"}},{"type":"interest","period":"long","time":{"type":"BigNumber","hex":"0x81"},"amount":{"type":"BigNumber","hex":"0x00"}},{"type":"interest","period":"long","time":{"type":"BigNumber","hex":"0x81"},"amount":{"type":"BigNumber","hex":"0x00"}},{"type":"interest","period":"long","time":{"type":"BigNumber","hex":"0x81"},"amount":{"type":"BigNumber","hex":"0x00"}},{"type":"interest","period":"long","time":{"type":"BigNumber","hex":"0x81"},"amount":{"type":"BigNumber","hex":"0x00"}},{"type":"interest","period":"long","time":{"type":"BigNumber","hex":"0x81"},"amount":{"type":"BigNumber","hex":"0x00"}},{"type":"interest","period":"long","time":{"type":"BigNumber","hex":"0x81"},"amount":{"type":"BigNumber","hex":"0x00"}},{"type":"interest","period":"long","time":{"type":"BigNumber","hex":"0x81"},"amount":{"type":"BigNumber","hex":"0x00"}},{"type":"interest","period":"long","time":{"type":"BigNumber","hex":"0x81"},"amount":{"type":"BigNumber","hex":"0x00"}},{"type":"interest","period":"long","time":{"type":"BigNumber","hex":"0x81"},"amount":{"type":"BigNumber","hex":"0x00"}},{"type":"interest","period":"long","time":{"type":"BigNumber","hex":"0x81"},"amount":{"type":"BigNumber","hex":"0x00"}},{"type":"interest","period":"long","time":{"type":"BigNumber","hex":"0x81"},"amount":{"type":"BigNumber","hex":"0x00"}},{"type":"interest","period":"long","time":{"type":"BigNumber","hex":"0x81"},"amount":{"type":"BigNumber","hex":"0x00"}},{"type":"interest","period":"long","time":{"type":"BigNumber","hex":"0x81"},"amount":{"type":"BigNumber","hex":"0x00"}},{"type":"interest","period":"long","time":{"type":"BigNumber","hex":"0x81"},"amount":{"type":"BigNumber","hex":"0x00"}},{"type":"interest","period":"long","time":{"type":"BigNumber","hex":"0x81"},"amount":{"type":"BigNumber","hex":"0x00"}},{"type":"interest","period":"long","time":{"type":"BigNumber","hex":"0x81"},"amount":{"type":"BigNumber","hex":"0x00"}},{"type":"interest","period":"long","time":{"type":"BigNumber","hex":"0x81"},"amount":{"type":"BigNumber","hex":"0x00"}},{"type":"interest","period":"long","time":{"type":"BigNumber","hex":"0x81"},"amount":{"type":"BigNumber","hex":"0x00"}},{"type":"interest","period":"long","time":{"type":"BigNumber","hex":"0x81"},"amount":{"type":"BigNumber","hex":"0x00"}}]}